linkml_datalog/__init__.py
linkml_datalog/dumpers/tupledumper.py
linkml_datalog/engines/__init__.py
linkml_datalog/engines/datalog_engine.py
linkml_datalog/generators/dataloggen.py
linkml_datalog/model/validation.py
linkml_datalog/utils/json_to_eav.py
linkml_datalog-0.2.0.dist-info/entry_points.txt
linkml_datalog-0.2.0.dist-info/WHEEL
linkml_datalog-0.2.0.dist-info/METADATA
linkml_datalog-0.2.0.dist-info/RECORD
